ntfy_api/__init__.py
ntfy_api/__version__.py
ntfy_api/_internals.py
ntfy_api/actions.py
ntfy_api/client.py
ntfy_api/creds.py
ntfy_api/enums.py
ntfy_api/errors.py
ntfy_api/filter.py
ntfy_api/message.py
ntfy_api/py.typed
ntfy_api/subscription.py
ntfy_logging/__init__.py
ntfy_logging/__init__.pyi
ntfy_logging/types.py
ntfy_logging-1.0.11.dist-info/LICENSE
ntfy_logging-1.0.11.dist-info/METADATA
ntfy_logging-1.0.11.dist-info/NOTICE
ntfy_logging-1.0.11.dist-info/WHEEL
ntfy_logging-1.0.11.dist-info/entry_points.txt
ntfy_logging-1.0.11.dist-info/RECORD
