Metadata-Version: 2.3
Name: ntfy-logging
Version: 1.0.11
Summary: A Python logging handler for sending logs to ntfy
License: GPL-3.0-or-later
Keywords: ntfy,logging,handler,python,log,notification,logger
Author: Aalen
Author-email: 65923772+MrAalen@users.noreply.github.com
Requires-Python: >=3.9
Classifier: Programming Language :: Python :: 3
Classifier: Programming Language :: Python :: 3.9
Classifier: Programming Language :: Python :: 3.10
Classifier: Programming Language :: Python :: 3.11
Classifier: Programming Language :: Python :: 3.12
Classifier: Programming Language :: Python :: 3.13
Classifier: License :: OSI Approved :: GNU General Public License v3 (GPLv3)
Classifier: Operating System :: OS Independent
Classifier: Intended Audience :: Developers
Classifier: Topic :: Software Development :: Libraries :: Python Modules
Classifier: Topic :: System :: Logging
Classifier: Development Status :: 5 - Production/Stable
Requires-Dist: httpx (>=0.28.1,<0.29.0)
Requires-Dist: typing-extensions (>=4.14.0,<5.0.0)
Requires-Dist: websockets (>=15.0.1,<16.0.0)
Project-URL: Bug Tracker, https://github.com/MrAalen/ntfy-logging/issues
Project-URL: Documentation, https://github.com/MrAalen/ntfy-logging#readme
Project-URL: Homepage, https://github.com/MrAalen/ntfy-logging
Project-URL: Repository, https://github.com/MrAalen/ntfy-logging
